swarmauri_storage_minio/__init__.py
swarmauri_storage_minio/minio_storage_adapter.py
swarmauri_storage_minio-0.2.0.dev4.dist-info/LICENSE
swarmauri_storage_minio-0.2.0.dev4.dist-info/METADATA
swarmauri_storage_minio-0.2.0.dev4.dist-info/WHEEL
swarmauri_storage_minio-0.2.0.dev4.dist-info/entry_points.txt
swarmauri_storage_minio-0.2.0.dev4.dist-info/RECORD
